gitermap/__init__.py
gitermap/_audio.py
gitermap/_context.py
gitermap/_process.py
gitermap/_tqdm_parallel.py
gitermap/_uniquecontext.py
gitermap/_utils.py
gitermap-0.3.0.dist-info/METADATA
gitermap-0.3.0.dist-info/WHEEL
gitermap-0.3.0.dist-info/top_level.txt
gitermap-0.3.0.dist-info/RECORD
