Metadata-Version: 2.1
Name: gitermap
Version: 0.3.0
Summary: Easy parallelizable and cacheable list comprehensions
Home-page: https://github.com/gregparkes/gitermap
Author: Gregory Parkes
Author-email: gregorymparkes@gmail.com
License: GPL-3.0
Platform: UNKNOWN
Classifier: Natural Language :: English
Classifier: Programming Language :: Python :: 3.8
Classifier: License :: OSI Approved :: GNU General Public License v3 (GPLv3)
Classifier: Framework :: Jupyter
Requires-Python: >=3.8
Requires-Dist: joblib (>=0.14.1)
